{
  "intents":[
    {
      "id":"saludo",
      "patterns":[
        "Buen día",
        "Buenas tardes",
        "Buenas noches",
        "Ey",
        "Hola"
      ],
      "responses":[
        "Buenas.",
        "¡Hola!",
        "Saludos humano."
      ]
    },
    {
      "id":"como-estas",
      "patterns":[
        "¿Como estás?",
        "¿Como te va?",
        "¿Que tal estás?",
        "¿Que onda?"
      ],
      "responses":[
        "Bien, gracias.",
        "No me quejo.",
        "Acá ando."
      ]
    },
    {
      "id":"humanidad",
      "patterns":[
        "¿Eres humano?",
        "¿Eres un chatbot?",
        "¿Eres un robot?",
        "¿Eres una persona?",
        "¿Que eres?",
        "¿Quién eres?"
      ],
      "responses":[
        "Soy un chatbot y orgulloso de serlo."
      ]
    },
    {
      "id":"hambre-pan-duro",
      "patterns":[
        "Almuerzo",
        "Cena",
        "Comida",
        "Hambre",
        "Merienda",
        "Pan duro"
      ],
      "responses":[
        "A buen hambre, no hay pan duro.",
        "Dios le da pan al que no tiene dientes." 
      ]
    },
    {
      "id":"oro-reluce",
      "patterns":[
        "Brillante",
        "Costoso",
        "Joyas",
        "Lujo",
        "Oro"
      ],
      "responses":[
        "No es oro todo lo que reluce."
      ]
    },
    {
      "id":"dejar-mañana",
      "patterns":[
        "No estudiar",
        "No trabajar",
        "Pereza",
        "Procastrinar"
      ],
      "responses":[
        "No dejes para mañana lo que puedas hacer hoy."
      ]
    },
    {
      "id":"ojo-x-ojo",
      "patterns":[
        "Vengar",
        "Venganza"
      ],
      "responses":[
        "Ojo por ojo y diente por diente.",
        "La venganza nunca buena, mata el alma y la envenena."
      ]
    },
    {
      "id":"abarcar-mucho",
      "patterns":[
        "Estudiar mucho",
        "Estudiar todo",
        "Hacer mucho",
        "Hacer todo"
      ],
      "responses":[
        "Poco aprieta quien mucho abarca.",
        "Mucho abarca el que poco aprieta."
      ]
    },
    {
      "id":"madrugar-amanece",
      "patterns":[
        "Acostar temprano",
        "Amanecer",
        "Despertar temprano",
        "Levantar temprano",
        "Madrugar"
      ],
      "responses":[
        "Por mucho madrugar no amanece más temprano."
      ]
    },
    {
      "id":"hierro-mata",
      "patterns":[
        "Acuchillar",
        "Asesinar",
        "Cuchillo",
        "Espada",
        "Hierro",
        "Matar"
      ],
      "responses":[
        "Quien a hierro mata, a hierro muere.",
        "El que a espada mata, a espada muere."
      ]
    },
    {
      "id":"vida-sin-amigos",
      "patterns":[
        "Amigos",
        "Amistad",
        "Funeral",
        "Muerte",
        "Testigos",
        "Vida y muerte"
      ],
      "responses":[
        "Vida sin amigos, muerte sin testigos."
      ]
    },
    {
      "id":"buena-vida-ira",
      "patterns":[
        "Estoy enojado",
        "Siento furia",
        "Siento ira",
        "Necesito tranquilidad"
      ],
      "responses":[
        "Vivirás buena vida si refrenas tu ira."
      ]
    },
    {
      "id":"zapatero",
      "patterns":[
        "Calzado",
        "Experto",
        "Zapatos"
      ],
      "responses":[
        "Zapatero, a tus zapatos."
      ]
    }
  ]
}